datajax/__init__.py
datajax/api/__init__.py
datajax/api/djit.py
datajax/api/sharding.py
datajax/api/transforms.py
datajax/cli/__init__.py
datajax/cli/export_wavespec.py
datajax/cli/replay_tuner.py
datajax/frame/__init__.py
datajax/frame/frame.py
datajax/io/__init__.py
datajax/io/exporter.py
datajax/io/parquet.py
datajax/ir/__init__.py
datajax/ir/graph.py
datajax/ir/serialize.py
datajax/jax_bridge/__init__.py
datajax/planner/__init__.py
datajax/planner/execute.py
datajax/planner/metrics.py
datajax/planner/optimizer.py
datajax/planner/plan.py
datajax/planner/replay.py
datajax/runtime/__init__.py
datajax/runtime/bodo_codegen.py
datajax/runtime/bodo_native.py
datajax/runtime/bodo_pipeline.py
datajax/runtime/bodo_plan.py
datajax/runtime/bodo_stub.py
datajax/runtime/executor.py
datajax/runtime/mesh.py
datajax/runtime/plan_diagnostics.py
datajax-0.0.1.dist-info/METADATA
datajax-0.0.1.dist-info/WHEEL
datajax-0.0.1.dist-info/entry_points.txt
datajax-0.0.1.dist-info/RECORD
