Metadata-Version: 2.4
Name: datajax
Version: 0.0.1
Summary: JAX-inspired dataframe transforms with Bodo-backed execution
Project-URL: Homepage, https://github.com/strangeloopcanon/datajax
Project-URL: Documentation, https://github.com/strangeloopcanon/datajax
Project-URL: Source, https://github.com/strangeloopcanon/datajax
Author: Rohit
License: Apache-2.0
Keywords: bodo,dataframe,jax,pandas,spmd
Classifier: Development Status :: 3 - Alpha
Classifier: Intended Audience :: Developers
Classifier: License :: OSI Approved :: Apache Software License
Classifier: Programming Language :: Python :: 3
Classifier: Programming Language :: Python :: 3.10
Classifier: Programming Language :: Python :: 3.11
Classifier: Programming Language :: Python :: 3.12
Classifier: Topic :: Scientific/Engineering :: Information Analysis
Requires-Python: >=3.10
Requires-Dist: bodo>=2024.1.0
Requires-Dist: numpy>=1.24
Requires-Dist: pandas>=2.0
Requires-Dist: pyarrow>=12.0
Provides-Extra: dev
Requires-Dist: mypy>=1.8; extra == 'dev'
Requires-Dist: pyright>=1.1; extra == 'dev'
Requires-Dist: pytest-cov>=4.0; extra == 'dev'
Requires-Dist: pytest-mock>=3.10; extra == 'dev'
Requires-Dist: pytest>=8.0; extra == 'dev'
Requires-Dist: ruff>=0.4; extra == 'dev'
